buildoutls/__init__.py
buildoutls/__main__.py
buildoutls/buildout.py
buildoutls/cli.py
buildoutls/code_actions.py
buildoutls/commands.py
buildoutls/diagnostic.py
buildoutls/jinja.py
buildoutls/profiling.py
buildoutls/recipes.py
buildoutls/semantic_tokens.py
buildoutls/server.py
buildoutls/types.py
buildoutls/bench/__init__.py
buildoutls/bench/slapos.py
buildoutls/tests/__init__.py
buildoutls/tests/conftest.py
buildoutls/tests/test_buildout_parser.py
buildoutls/tests/test_code_actions.py
buildoutls/tests/test_completion.py
buildoutls/tests/test_definition.py
buildoutls/tests/test_diagnostics.py
buildoutls/tests/test_document_link.py
buildoutls/tests/test_document_symbol.py
buildoutls/tests/test_hover.py
buildoutls/tests/test_jinja.py
buildoutls/tests/test_references.py
buildoutls/tests/test_semantic_tokens.py
buildoutls/tests/test_slapos.py
buildoutls/util/__init__.py
buildoutls/util/aiohttp_session.py
buildoutls/util/md5sum.py
buildoutls/util/pypi.py
zc_buildout_languageserver-0.17.2.dist-info/licenses/LICENCE.txt
zc_buildout_languageserver-0.17.2.dist-info/METADATA
zc_buildout_languageserver-0.17.2.dist-info/WHEEL
zc_buildout_languageserver-0.17.2.dist-info/entry_points.txt
zc_buildout_languageserver-0.17.2.dist-info/top_level.txt
zc_buildout_languageserver-0.17.2.dist-info/RECORD
