Metadata-Version: 2.4
Name: zc.buildout.languageserver
Version: 0.17.2
Summary: A language server for zc.buildout
License: Permission is hereby granted, free of charge, to any person obtaining a
Project-URL: Source code, https://github.com/perrinjerome/vscode-zc-buildout/
Project-URL: Changelog, https://github.com/perrinjerome/vscode-zc-buildout/tree/main/server/CHANGELOG.md
Keywords: buildout,language-server,lsp
Classifier: Intended Audience :: Developers
Classifier: Topic :: Software Development
Classifier: Framework :: Buildout
Classifier: License :: OSI Approved :: MIT License
Classifier: Programming Language :: Python :: 3
Requires-Python: >=3.9
License-File: LICENCE.txt
Requires-Dist: aiohttp
Requires-Dist: cachetools
Requires-Dist: packaging
Requires-Dist: pygls>=2.0.0
Requires-Dist: pygments
Requires-Dist: typing-extensions
Requires-Dist: zc.buildout
Provides-Extra: test
Requires-Dist: aioresponses; extra == "test"
Requires-Dist: coverage; extra == "test"
Requires-Dist: mypy; extra == "test"
Requires-Dist: pylint; extra == "test"
Requires-Dist: pytest-asyncio; extra == "test"
Requires-Dist: pytest-benchmark; extra == "test"
Requires-Dist: pytest-cov; extra == "test"
Requires-Dist: pytest; extra == "test"
Requires-Dist: types-cachetools; extra == "test"
Requires-Dist: types-pygments; extra == "test"
Requires-Dist: types-setuptools; extra == "test"
Requires-Dist: types-toml; extra == "test"
Requires-Dist: ruff; extra == "test"
Dynamic: license-file
